ecological/__init__.py
ecological/config.py
ecological/transform.py
ecological-3.0.1.dist-info/METADATA
ecological-3.0.1.dist-info/WHEEL
ecological-3.0.1.dist-info/licenses/LICENSE
ecological-3.0.1.dist-info/RECORD
