Metadata-Version: 2.4
Name: ecological
Version: 3.0.1
Summary: Map a Python configuration from environment variables
Project-URL: Homepage, https://github.com/jmcs/ecological
Project-URL: Repository, https://github.com/jmcs/ecological
Author-email: João Santos <jmcs@jsantos.eu>, Marcin Zaremba <mrcn.zrmb@gmail.com>
License: MIT License
License-File: LICENSE
Classifier: Development Status :: 4 - Beta
Classifier: Intended Audience :: Developers
Classifier: Operating System :: OS Independent
Classifier: Programming Language :: Python
Requires-Python: >=3.10
